qrscan/__init__.py
qrscan/main.kv
qrscan/main.py
qrscan/version.py
QrScan-2020.528.dist-info/LICENSE
QrScan-2020.528.dist-info/METADATA
QrScan-2020.528.dist-info/WHEEL
QrScan-2020.528.dist-info/entry_points.txt
QrScan-2020.528.dist-info/top_level.txt
QrScan-2020.528.dist-info/RECORD
