Metadata-Version: 2.1
Name: QrScan
Version: 2020.528
Summary: QR Code & Barcode scanner cross-platform application
Home-page: https://github.com/AndreMiras/QrScan
Author: Andre Miras
License: UNKNOWN
Platform: UNKNOWN
Requires-Python: >=3
Requires-Dist: kivy-garden.kivymd
Requires-Dist: opencv-python (>=4)
Requires-Dist: raven
Requires-Dist: validators
Requires-Dist: zbarcam
